{
  "source": {
    "url": "https://ek.ua/ua/SAMSUNG-BESPOKE-RB34C7B5D39.htm",
    "actual_url": "https://ek.ua/ua/SAMSUNG-BESPOKE-RB34C7B5D39.htm",
    "site": "E-Katalog",
    "retrieved_on": "2026-03-09"
  },
  "product": {
    "brand": "Samsung",
    "model": "BeSpoke RB34C7B5D39 бежевий",
    "title": "Холодильник Samsung BeSpoke RB34C7B5D39 бежевий",
    "category": "E-Katalog category 200",
    "year": 2024,
    "color": null
  },
  "pricing": {
    "currency": "UAH",
    "min_price": null,
    "max_price": null,
    "offers_count": 39
  },
  "summary": {
    "type": null,
    "total_volume_l": 344,
    "cameras_count": 2,
    "cooling_circuits": 2,
    "compressors_count": 1,
    "no_frost": {
      "fridge": true,
      "freezer": true
    }
  },
  "features": {
    "display": null,
    "door_open_indicator": true,
    "hidden_door_handles": true,
    "fresh_zone": null,
    "dynamic_cooling": false,
    "auto_defrost": false,
    "led_lighting": true,
    "quick_freeze": false,
    "leak_protection": null,
    "foam_control": null,
    "imbalance_control": null,
    "child_lock": null
  },
  "fridge_compartment": {
    "volume_l": 230,
    "shelves_count": 4
  },
  "freezer_compartment": {
    "location": "знизу",
    "volume_l": 114,
    "sections_count": 3,
    "sections_details": "3 шт",
    "cold_storage_time_h": 9,
    "freezing_capacity_kg_per_day": 8
  },
  "general": {
    "control": "сенсорне внутрішнє",
    "energy_class_new": "D",
    "annual_energy_consumption_kwh": 204,
    "climate_class": [
      "SN",
      "N",
      "ST",
      "T"
    ],
    "working_temperature_range_c": {
      "min": null,
      "max": null
    },
    "noise_level_db": 35,
    "dimensions_cm": {
      "height": 185.3,
      "width": 59.5,
      "depth": 65.8
    },
    "weight_kg": 72.0,
    "country_of_origin": null
  },
  "metadata": {
    "language": "ua",
    "html_lang": "uk",
    "parsed_groups": [
      "general",
      "Ціни на Samsung BeSpoke RB34C7B5D39"
    ]
  },
  "description": "Холодильник Samsung BeSpoke RB34C7B5D39 бежевий за ціною від 50772 до 50772 грн. >>> E-Katalog - каталог порівняння цін та характеристик ✔ Відгуки, огляди, інструкції.",
  "images": [
    "https://s.ek.ua/jpg_zoom1/2612874.jpg",
    "https://mzimg.com/big/91/hm4y6gl6591.jpg",
    "https://mzimg.com/big/j1/hm4y6gmfij1.jpg",
    "https://mzimg.com/big/h1/hkmw19e36h1.jpg",
    "https://mzimg.com/big/31/hkmw19i3631.jpg",
    "https://mzimg.com/big/01/hkmw19oq001.jpg",
    "https://mzimg.com/big/q1/hkmw19tczq1.jpg",
    "https://mzimg.com/big/r1/hkmw19yrkr1.jpg",
    "https://mzimg.com/big/l1/hkmw1a7bsl1.jpg",
    "https://mzimg.com/big/k1/hkmw1abc6k1.jpg",
    "https://mzimg.com/big/z1/hkmw1ajolz1.jpg",
    "https://mzimg.com/big/91/hkmw1anae91.jpg",
    "https://s.ek.ua/jpg/2612874.jpg"
  ],
  "raw_specs": {
    "general": {
      "Фото 14": "50 772 грн. Купити! Холодильник Samsung Bespoke RB34C7B5D39 inSale.com.ua Менше року Доставка: у Дніпро з Києва Гарантія: 12 міс. Поскаржитись в список мої списки додати до порівняння",
      "Колір Загальний об'єм 344 л Кількість камер 2 Контурів охолодження 2 Компресорів 1 Інверторний компресор No Frost морозильна / холодильна камери Функції та можливості Функції режим відпустки керування зі смартфона (Wi-Fi) LED дисплей індикатор закриття дверцят перевішування дверей Додатково приховані ручки дверей змінні декоративні панелі Холодильне відділення Об'єм холодильної камери 230 л Полиць 4 шт Відсіки для зберігання зона свіжості / Optimal Fresh+ / зона вологості / Humidity Fresh+ / Швидке охолодження Динамічне охолодження Автоматичне розморожування LED освітлення": "січень 2024",
      "Загальний об'єм": "344 л",
      "Кількість камер": "2",
      "Контурів охолодження": "2",
      "Компресорів": "1",
      "No Frost": "морозильна / холодильна камери",
      "Функції": "режим відпустки керування зі смартфона (Wi-Fi) LED дисплей індикатор закриття дверцят перевішування дверей",
      "Додатково": "приховані ручки дверей змінні декоративні панелі",
      "Об'єм холодильної камери": "230 л",
      "Полиць": "4 шт",
      "Відсіки для зберігання": "зона свіжості / Optimal Fresh+ / зона вологості / Humidity Fresh+ /",
      "Морозильна камера": "знизу",
      "Об'єм морозильної камери": "114 л",
      "Відділень морозильної камери": "3 шт",
      "Температура морозилки": "-23 °C",
      "Час збереження холоду": "9 год",
      "Потужність заморожування": "8 кг/добу",
      "Управління": "сенсорне внутрішнє",
      "Клас енергоспоживання (new)": "D",
      "Споживання енергії в рік": "204 кВт*год",
      "Кліматичний клас": "SN, N, ST, T (+10...+43 °С)",
      "Клас гучності": "B",
      "Рівень шуму": "35 дБ",
      "Габарити (ВхШхГ)": "185.3x59.5x65.8 см",
      "Вага": "72 кг",
      "Офіційний сайт": "samsung.com",
      "Дата додавання на E-Katalog": "січень 2024",
      "Інверторний компресор": "так",
      "Швидке охолодження": "так",
      "Динамічне охолодження": "так",
      "Автоматичне розморожування": "так",
      "LED освітлення": "так"
    },
    "Ціни на Samsung BeSpoke RB34C7B5D39": {}
  },
  "local_images": [
    "missing_refrigerators\\samsung_bespoke_rb34c7b5d39\\images\\01.jpg",
    "missing_refrigerators\\samsung_bespoke_rb34c7b5d39\\images\\02.jpg",
    "missing_refrigerators\\samsung_bespoke_rb34c7b5d39\\images\\03.jpg",
    "missing_refrigerators\\samsung_bespoke_rb34c7b5d39\\images\\04.jpg",
    "missing_refrigerators\\samsung_bespoke_rb34c7b5d39\\images\\05.jpg",
    "missing_refrigerators\\samsung_bespoke_rb34c7b5d39\\images\\06.jpg",
    "missing_refrigerators\\samsung_bespoke_rb34c7b5d39\\images\\07.jpg",
    "missing_refrigerators\\samsung_bespoke_rb34c7b5d39\\images\\08.jpg",
    "missing_refrigerators\\samsung_bespoke_rb34c7b5d39\\images\\09.jpg",
    "missing_refrigerators\\samsung_bespoke_rb34c7b5d39\\images\\10.jpg",
    "missing_refrigerators\\samsung_bespoke_rb34c7b5d39\\images\\11.jpg",
    "missing_refrigerators\\samsung_bespoke_rb34c7b5d39\\images\\12.jpg",
    "missing_refrigerators\\samsung_bespoke_rb34c7b5d39\\images\\13.jpg"
  ]
}