{
  "source": {
    "url": "https://ek.ua/SAMSUNG-BESPOKE-RB34A6B4FAP.htm",
    "actual_url": "https://ek.ua/SAMSUNG-BESPOKE-RB34A6B4FAP.htm",
    "site": "E-Katalog",
    "retrieved_on": "2026-03-09"
  },
  "product": {
    "brand": "Samsung",
    "model": "BeSpoke RB34A6B4FAP",
    "title": "Холодильник Samsung BeSpoke RB34A6B4FAP",
    "category": "E-Katalog category 200",
    "year": 2021,
    "color": null
  },
  "pricing": {
    "currency": "UAH",
    "min_price": null,
    "max_price": null,
    "offers_count": null
  },
  "summary": {
    "type": null,
    "total_volume_l": 340,
    "cameras_count": 2,
    "cooling_circuits": 2,
    "compressors_count": 1,
    "no_frost": {
      "fridge": true,
      "freezer": true
    }
  },
  "features": {
    "display": null,
    "door_open_indicator": true,
    "hidden_door_handles": true,
    "fresh_zone": null,
    "dynamic_cooling": false,
    "auto_defrost": false,
    "led_lighting": false,
    "quick_freeze": false,
    "leak_protection": null,
    "foam_control": null,
    "imbalance_control": null,
    "child_lock": null
  },
  "fridge_compartment": {
    "volume_l": 228,
    "shelves_count": 4
  },
  "freezer_compartment": {
    "location": "снизу",
    "volume_l": 112,
    "sections_count": 3,
    "sections_details": "3 шт",
    "cold_storage_time_h": null,
    "freezing_capacity_kg_per_day": null
  },
  "general": {
    "control": "сенсорное внутреннее",
    "energy_class_new": "F",
    "annual_energy_consumption_kwh": 295,
    "climate_class": [
      "SN",
      "N",
      "ST",
      "T"
    ],
    "working_temperature_range_c": {
      "min": null,
      "max": null
    },
    "noise_level_db": 37,
    "dimensions_cm": {
      "height": 185.3,
      "width": 59.5,
      "depth": 65.8
    },
    "weight_kg": 65.0,
    "country_of_origin": "Польша"
  },
  "metadata": {
    "language": "ru",
    "html_lang": "ru",
    "parsed_groups": [
      "general"
    ]
  },
  "description": "Уникальный в своем роде холодильник, который кроме продвинутого оснащения и продуманной эргономики, может также похвастаться возможностью стилизации при помощи специальных декоративных панелей, что позволяет «модифицировать» внешний вид устройства таким образом, чтобы максимально соответствовать интерьеру кухни. Технология SpaceMax обеспечивает лучшую теплоизоляцию стенок, благодаря чему модель может похвастаться увеличенной вместимостью камер при сохранении типичных размеров корпуса. Среди прочего холодильник Samsung BeSpoke RB34A6B4FAP может похвастаться надежным инверторным компрессором, раздельными контурами охлаждения для каждой из камер, а также полной поддержкой технологии Full No Frost, которая предотвращает образование внутри льда и инея. Общий полезный объем модели составляет 340 л. Холодильное отделение может похвастаться специальной регулируемой зоной влажности (Humidity Fresh+), полкой для бутылок, а также продвинутой системой динамического охлаждения All-Around Cooling. Морозилка на 112 л размещена снизу и отличается поддержкой функции быстрой заморозки Power Freeze. Задняя панель холодильника представляет собой полностью ровную защитную крышку, которая выглядит максимально аккуратно, легко очищается и обеспечивает дополнительную долговечность устройству.",
  "images": [
    "https://s.ek.ua/jpg_zoom1/2038595.jpg",
    "https://mzimg.com/big/41/gri2gsicx41.jpg",
    "https://s.ek.ua/jpg/2038595.jpg"
  ],
  "raw_specs": {
    "general": {
      "Tv-mir.com.ua →": "26 871 грн.",
      "Основное Общий объем 340 л Количество камер 2 Контуров охлаждения 2 Компрессоров 1 Инверторный компрессор No Frost морозильная / холодильная камеры Функции и возможности Функции индикатор закрытия дверцы перевешивание дверей Дополнительно скрытые дверные ручки сменные декоративные панели / BeSpoke / Холодильное отделение Объем холодильной камеры 228 л Полок 4 шт Отсеки для хранения зона свежести зона влажности полка для бутылок Быстрое охлаждение Динамическое охлаждение Автоматическая разморозка LED освещение": "июнь 2021",
      "Общий объем": "340 л",
      "Количество камер": "2",
      "Контуров охлаждения": "2",
      "Компрессоров": "1",
      "No Frost": "морозильная / холодильная камеры",
      "Функции": "индикатор закрытия дверцы перевешивание дверей",
      "Дополнительно": "скрытые дверные ручки сменные декоративные панели / BeSpoke /",
      "Объем холодильной камеры": "228 л",
      "Полок": "4 шт",
      "Отсеки для хранения": "зона свежести зона влажности полка для бутылок",
      "Морозильная камера": "снизу",
      "Объем морозильной камеры": "112 л",
      "Отделений морозильной камеры": "3 шт",
      "Температура морозилки": "-23 °C",
      "Управление": "сенсорное внутреннее",
      "Класс энергопотребления (new)": "F",
      "Потребление энергии в год": "295 кВт*ч",
      "Климатический класс": "SN, N, ST, T (+10...+43 °С)",
      "Уровень шума": "37 дБ",
      "Габариты (ВхШхГ)": "185.3x59.5x65.8 см",
      "Вес": "65 кг",
      "Страна производства": "Польша",
      "Официальный сайт": "samsung.com",
      "Дата добавления на E-Katalog": "июнь 2021",
      "Инверторный компрессор": "да",
      "Быстрое охлаждение": "да",
      "Динамическое охлаждение": "да",
      "Автоматическая разморозка": "да",
      "LED освещение": "да"
    }
  },
  "local_images": [
    "missing_refrigerators\\samsung_bespoke_rb34a6b4fap\\images\\01.jpg",
    "missing_refrigerators\\samsung_bespoke_rb34a6b4fap\\images\\02.jpg",
    "missing_refrigerators\\samsung_bespoke_rb34a6b4fap\\images\\03.jpg"
  ]
}