{
  "source": {
    "url": "https://ek.ua/en/ELEYUS-HRNW-2180E55-SV.htm",
    "actual_url": "https://ek.ua/en/ELEYUS-HRNW-2180E55-SV.htm",
    "site": "E-Katalog",
    "retrieved_on": "2026-03-09"
  },
  "product": {
    "brand": "ELEYUS",
    "model": "HRNW 2180E55 SV silver",
    "title": "ELEYUS HRNW 2180E55 SV silver",
    "category": "E-Katalog category 200",
    "year": 256,
    "color": null
  },
  "pricing": {
    "currency": "UAH",
    "min_price": null,
    "max_price": null,
    "offers_count": 18
  },
  "summary": {
    "type": null,
    "total_volume_l": null,
    "cameras_count": null,
    "cooling_circuits": 2,
    "compressors_count": 1,
    "no_frost": {
      "fridge": null,
      "freezer": null
    }
  },
  "features": {
    "display": null,
    "door_open_indicator": null,
    "hidden_door_handles": null,
    "fresh_zone": null,
    "dynamic_cooling": null,
    "auto_defrost": null,
    "led_lighting": null,
    "quick_freeze": null,
    "leak_protection": null,
    "foam_control": null,
    "imbalance_control": null,
    "child_lock": null
  },
  "fridge_compartment": {
    "volume_l": null,
    "shelves_count": 4
  },
  "freezer_compartment": {
    "location": "bottom",
    "volume_l": null,
    "sections_count": 3,
    "sections_details": "3",
    "cold_storage_time_h": null,
    "freezing_capacity_kg_per_day": null
  },
  "general": {
    "control": "rotary knobs",
    "energy_class_new": "A+",
    "annual_energy_consumption_kwh": 256,
    "climate_class": null,
    "working_temperature_range_c": {
      "min": null,
      "max": null
    },
    "noise_level_db": 42,
    "dimensions_cm": {
      "height": 181.0,
      "width": 54.5,
      "depth": 59.6
    },
    "weight_kg": 51.0,
    "country_of_origin": "China"
  },
  "metadata": {
    "language": "en",
    "html_lang": "en",
    "parsed_groups": [
      "general",
      "Price for ELEYUS HRNW 2180E55 SV"
    ]
  },
  "description": "Fridge ELEYUS HRNW 2180E55 SV silver at a price from 14922 to 17120 ₴ >>> E-Katalog - catalog prices comparison & specs ✔ User & media reviews, manuals.",
  "images": [
    "https://s.ek.ua/jpg_zoom1/2811572.jpg",
    "https://mzimg.com/big/c1/hw823zbn8c1.jpg",
    "https://mzimg.com/big/e1/hw823zc8je1.jpg",
    "https://mzimg.com/big/k1/hw823zvoxk1.jpg",
    "https://mzimg.com/big/g1/hw823zynag1.jpg",
    "https://mzimg.com/big/x1/hw8240ll7x1.jpg",
    "https://mzimg.com/big/q1/hw8240rlhq1.jpg",
    "https://mzimg.com/big/y1/hw82417uty1.jpg",
    "https://mzimg.com/big/m1/hw8241aujm1.jpg",
    "https://mzimg.com/big/o1/hw8241qpco1.jpg",
    "https://mzimg.com/big/g1/hw8241seug1.jpg",
    "https://mzimg.com/big/e1/hw8242gaie1.jpg",
    "https://s.ek.ua/jpg/2811572.jpg"
  ],
  "raw_specs": {
    "general": {
      "Photos 17": "16 039 ₴",
      "Pro100market.com.ua →": "15 706 ₴",
      "FOXTROT.UA →": "15 073 ₴",
      "Elmag.ua →": "15 558 ₴",
      "Comtrading.ua →": "16 039 ₴",
      "АЛЛО →": "16 039 ₴",
      "Colour Total capacity 237 L Number of chambers 2 Number of cooling circuits 2 Number of compressors 1 No Frost freezer / refrigerator compartments Features Features reversible door More features hidden door handles Refrigeration chamber Refrigerator capacity 182 L Number of shelves 4 Dynamic air cooling Auto-defrost LED lighting": "December 2024",
      "Total capacity": "237 L",
      "Number of chambers": "2",
      "Number of cooling circuits": "2",
      "Number of compressors": "1",
      "No Frost": "freezer / refrigerator compartments",
      "Features": "reversible door",
      "More features": "hidden door handles",
      "Refrigerator capacity": "182 L",
      "Number of shelves": "4",
      "Freezer compartment": "bottom",
      "Freezer capacity": "55 L",
      "Freezer drawers": "3",
      "Autonomy time": "12 h",
      "Freeze capacity": "2.5 kg/day",
      "Controls": "rotary knobs",
      "Energy class": "A+",
      "Energy consumption per year": "256 kWh",
      "Noise level": "42 dB",
      "Dimensions (HxWxD)": "181x54.5x59.6 cm",
      "Weight": "51 kg",
      "Country of origin": "China",
      "Official Website": "eleyus.com",
      "Added to E-Catalog": "December 2024",
      "LED lighting": "yes",
      "Dynamic air cooling": "yes",
      "Auto-defrost": "yes"
    },
    "Price for ELEYUS HRNW 2180E55 SV": {}
  },
  "local_images": [
    "missing_refrigerators\\eleyus_hrnw_2180e55_sv\\images\\01.jpg",
    "missing_refrigerators\\eleyus_hrnw_2180e55_sv\\images\\02.jpg",
    "missing_refrigerators\\eleyus_hrnw_2180e55_sv\\images\\03.jpg",
    "missing_refrigerators\\eleyus_hrnw_2180e55_sv\\images\\04.jpg",
    "missing_refrigerators\\eleyus_hrnw_2180e55_sv\\images\\05.jpg",
    "missing_refrigerators\\eleyus_hrnw_2180e55_sv\\images\\06.jpg",
    "missing_refrigerators\\eleyus_hrnw_2180e55_sv\\images\\07.jpg",
    "missing_refrigerators\\eleyus_hrnw_2180e55_sv\\images\\08.jpg",
    "missing_refrigerators\\eleyus_hrnw_2180e55_sv\\images\\09.jpg",
    "missing_refrigerators\\eleyus_hrnw_2180e55_sv\\images\\10.jpg",
    "missing_refrigerators\\eleyus_hrnw_2180e55_sv\\images\\11.jpg",
    "missing_refrigerators\\eleyus_hrnw_2180e55_sv\\images\\12.jpg",
    "missing_refrigerators\\eleyus_hrnw_2180e55_sv\\images\\13.jpg"
  ]
}